{
  "lesson_id": "eiken-2-84",
  "title": "Lesson 84",
  "words": [
    {
      "word": "challenge",
      "meaning": "to question or dispute",
      "japaneseMeaning": "挑戦する、異議を唱える",
      "synonyms": "question, confront",
      "antonyms": "accept, comply",
      "forms": "challenge, challenges, challenging, challenged",
      "example": "They challenged the decision."
    },
    {
      "word": "clarify",
      "meaning": "to make something easier to understand",
      "japaneseMeaning": "明確にする、わかりやすくする",
      "synonyms": "explain, clear up",
      "antonyms": "confuse, hide",
      "forms": "clarify, clarifies, clarifying, clarified",
      "example": "Please clarify the rules before the game starts."
    },
    {
      "word": "rehearse",
      "meaning": "to practice for a performance or presentation",
      "japaneseMeaning": "リハーサルをする、練習する",
      "synonyms": "practice, prepare",
      "antonyms": "improvise, neglect",
      "forms": "rehearse, rehearses, rehearsing, rehearsed",
      "example": "We rehearsed our presentation after school."
    },
    {
      "word": "support",
      "meaning": "to back up an idea or person",
      "japaneseMeaning": "支援する",
      "synonyms": "endorse, assist",
      "antonyms": "oppose, reject",
      "forms": "support, supports, supporting, supported",
      "example": "He supported his friend's argument."
    },
    {
      "word": "define",
      "meaning": "to explain the meaning of a word or idea",
      "japaneseMeaning": "定義する、意味を説明する",
      "synonyms": "explain, describe",
      "antonyms": "confuse, mix up",
      "forms": "define, defines, defining, defined",
      "example": "The teacher asked us to define the new term."
    },
    {
      "word": "possess",
      "meaning": "to have or own something",
      "japaneseMeaning": "所有する、持っている",
      "synonyms": "own, have",
      "antonyms": "lack, lose",
      "forms": "possess, possesses, possessing, possessed",
      "example": "Applicants must possess basic computer skills."
    },
    {
      "word": "steer",
      "meaning": "to control the direction of a vehicle or plan",
      "japaneseMeaning": "操縦する、導く",
      "synonyms": "guide, direct",
      "antonyms": "follow, drift",
      "forms": "steer, steers, steering, steered",
      "example": "She steered the boat away from the rocks."
    },
    {
      "word": "inspire",
      "meaning": "to motivate or encourage",
      "japaneseMeaning": "鼓舞する",
      "synonyms": "motivate, stimulate",
      "antonyms": "discourage, demotivate",
      "forms": "inspire, inspires, inspiring, inspired",
      "example": "His speech inspired the students."
    },
    {
      "word": "contrast",
      "meaning": "to compare differences",
      "japaneseMeaning": "対比する",
      "synonyms": "compare, differ",
      "antonyms": "match, resemble",
      "forms": "contrast, contrasts, contrasting, contrasted",
      "example": "The report contrasts city life with country life."
    },
    {
      "word": "release",
      "meaning": "to let someone or something go free, or make something public",
      "japaneseMeaning": "解放する、公開する",
      "synonyms": "free, publish",
      "antonyms": "hold, keep",
      "forms": "release, releases, releasing, released",
      "example": "The band will release a new song next month."
    }
  ]
}
