{
  "lesson_id": "eiken-2-67",
  "title": "Lesson 67",
  "paragraph": "This lesson focuses on practical B1 vocabulary for everyday communication.",
  "words": [
    {
      "word": "arrange",
      "meaning": "to plan or put things in order",
      "japaneseMeaning": "手配する、整理する",
      "synonyms": "do, perform",
      "antonyms": "stop, avoid",
      "forms": "arrange, arranges, arranging, arranged",
      "example": "We arrange the chairs before the meeting."
    },
    {
      "word": "verify",
      "meaning": "to check that something is true or correct",
      "japaneseMeaning": "確認する",
      "synonyms": "do, perform",
      "antonyms": "stop, avoid",
      "forms": "verify, verifys, verifying, verifyed",
      "example": "Verify the time before you leave."
    },
    {
      "word": "contact",
      "meaning": "to communicate with someone",
      "japaneseMeaning": "連絡する",
      "synonyms": "do, perform",
      "antonyms": "stop, avoid",
      "forms": "contact, contacts, contacting, contacted",
      "example": "Contact the office if you are late."
    },
    {
      "word": "discuss",
      "meaning": "to talk about something with others",
      "japaneseMeaning": "話し合う",
      "synonyms": "do, perform",
      "antonyms": "stop, avoid",
      "forms": "discuss, discusss, discussing, discussed",
      "example": "We discuss the plan after lunch."
    },
    {
      "word": "estimate",
      "meaning": "to guess an amount using information",
      "japaneseMeaning": "見積もる、推定する",
      "synonyms": "do, perform",
      "antonyms": "stop, avoid",
      "forms": "estimate, estimates, estimating, estimated",
      "example": "The builder will estimate the cost today."
    },
    {
      "word": "inform",
      "meaning": "to tell someone information",
      "japaneseMeaning": "知らせる",
      "synonyms": "do, perform",
      "antonyms": "stop, avoid",
      "forms": "inform, informs, informing, informed",
      "example": "Please inform the teacher about your absence."
    },
    {
      "word": "organize",
      "meaning": "to plan or arrange things well",
      "japaneseMeaning": "整理する、企画する",
      "synonyms": "do, perform",
      "antonyms": "stop, avoid",
      "forms": "organize, organizes, organizing, organized",
      "example": "Students organize a concert every year."
    },
    {
      "word": "prepare",
      "meaning": "to make ready",
      "japaneseMeaning": "準備する",
      "synonyms": "do, perform",
      "antonyms": "stop, avoid",
      "forms": "prepare, prepares, preparing, prepared",
      "example": "I prepare my bag before bed."
    },
    {
      "word": "notify",
      "meaning": "to tell someone officially or clearly",
      "japaneseMeaning": "知らせる",
      "synonyms": "do, perform",
      "antonyms": "stop, avoid",
      "forms": "notify, notifys, notifying, notifyed",
      "example": "Notify the office if your address changes."
    },
    {
      "word": "submit",
      "meaning": "to give work or documents officially",
      "japaneseMeaning": "提出する",
      "synonyms": "do, perform",
      "antonyms": "stop, avoid",
      "forms": "submit, submits, submiting, submited",
      "example": "Submit your report before noon."
    }
  ]
}
